Aula 14/adder/adders.v
`timescale 1ns/1ps
// Somadores para usar no exercício.
// NÃO envie este arquivo para o juiz, ele já tem estes módulos.
module ha (
    input a,
    input b,
    output s,
    output co
);
    assign #5 s = a ^ b;
    assign #2 co = a & b;
endmodule

module fa (
    input a,
    input b,
    input ci,
    output s,
    output co
);
    wire axorb, and1, and2;
    assign #5 axorb = a ^ b;
    assign #5 s = axorb ^ ci;
    assign #2 and1 = axorb & ci;
    assign #2 and2 = a & b;
    assign #2 co = and1 | and2;
endmodule

Aula 14/adder/adder_rc.v
module adder_rc 
    #(parameter N=4)
     (input [N-1:0] a,
      input [N-1:0] b,
      input ci,
      output [N-1:0] s,
      output co);
    // Escreva sua solução a partir daqui
    wire [N-1:0] carry;
    genvar i;
    generate
      for (i = 0; i < N; i = i + 1) begin
        // Instantiate a single-bit full adder for each bit position
        fa fa_inst (
          .a(a[i]),
          .b(b[i]),
          .ci((i != 0) ? carry[i-1] : 1'b0), 
          .s(s[i]),
          .co(carry[i])
        );
      end
      assign co = carry[N-1];
    endgenerate

endmodule

Aula 14/adder/adder_rc_tb.v
`timescale 1ns/1ps

module adder_rc_tb;

    parameter N = 5;
    reg [N-1:0] a;
    reg [N-1:0] b;
    reg ci;
    wire [N-1:0] s;
    wire co;

    adder_rc #(N) dut_rca(
        .a(a),
        .b(b),
        .ci(ci),
        .s(s),
        .co(co)
    );

  initial begin
    $dumpfile ("adder_rc_tb.vcd");
    $dumpvars(0, adder_rc_tb);
    // Initialize inputs
    a = 4'b0000;
    b = 4'b0000;
    ci = 0;
    //integer i;

    // Apply inputs and observe outputs
    $display("s must start at 00000 and increment by 1 after each line");
    $display("Time a b ci | s co");
    $display("--------------------");
    for (integer i = 0; i < 32; i = i + 1) begin
      #100; // Wait for one clock cycle
      $display("%t %b %b  %b | %b  %b", $time, a, b, ci, s, co);
      // Increment inputs for the next iteration
      a = a + 2;
      b = b - 1;
      ci = ~ci;
    end

    $finish; // End simulation
  end
    
endmodule

Aula 14/adder/adder_rc_tb.vcd
$date
	Fri Oct  6 23:40:11 2023
$end
$version
	Icarus Verilog
$end
$timescale
	1ps
$end
$scope module adder_rc_tb $end
$var wire 5 ! s [4:0] $end
$var wire 1 " co $end
$var reg 5 # a [4:0] $end
$var reg 5 $ b [4:0] $end
$var reg 1 % ci $end
$scope module dut_rca $end
$var wire 5 & a [4:0] $end
$var wire 5 ' b [4:0] $end
$var wire 1 % ci $end
$var wire 5 ( s [4:0] $end
$var wire 1 " co $end
$var wire 5 ) carry [4:0] $end
$scope begin genblk1[0] $end
$scope module fa_inst $end
$var wire 1 * a $end
$var wire 1 + and1 $end
$var wire 1 , and2 $end
$var wire 1 - axorb $end
$var wire 1 . b $end
$var wire 1 / ci $end
$var wire 1 0 co $end
$var wire 1 1 s $end
$upscope $end
$upscope $end
$scope begin genblk1[1] $end
$scope module fa_inst $end
$var wire 1 2 a $end
$var wire 1 3 and1 $end
$var wire 1 4 and2 $end
$var wire 1 5 axorb $end
$var wire 1 6 b $end
$var wire 1 7 ci $end
$var wire 1 8 co $end
$var wire 1 9 s $end
$upscope $end
$upscope $end
$scope begin genblk1[2] $end
$scope module fa_inst $end
$var wire 1 : a $end
$var wire 1 ; and1 $end
$var wire 1 < and2 $end
$var wire 1 = axorb $end
$var wire 1 > b $end
$var wire 1 ? ci $end
$var wire 1 @ co $end
$var wire 1 A s $end
$upscope $end
$upscope $end
$scope begin genblk1[3] $end
$scope module fa_inst $end
$var wire 1 B a $end
$var wire 1 C and1 $end
$var wire 1 D and2 $end
$var wire 1 E axorb $end
$var wire 1 F b $end
$var wire 1 G ci $end
$var wire 1 H co $end
$var wire 1 I s $end
$upscope $end
$upscope $end
$scope begin genblk1[4] $end
$scope module fa_inst $end
$var wire 1 J a $end
$var wire 1 K and1 $end
$var wire 1 L and2 $end
$var wire 1 M axorb $end
$var wire 1 N b $end
$var wire 1 O ci $end
$var wire 1 P co $end
$var wire 1 Q s $end
$upscope $end
$upscope $end
$upscope $end
$scope begin $ivl_for_loop0 $end
$var integer 32 R i [31:0] $end
$upscope $end
$upscope $end
$enddefinitions $end
#0
$dumpvars
b0 R
xQ
xP
xO
0N
xM
xL
xK
0J
xI
xH
xG
0F
xE
xD
xC
0B
xA
x@
x?
0>
x=
x<
x;
0:
x9
x8
x7
06
x5
x4
x3
02
x1
x0
0/
0.
x-
x,
x+
0*
bx )
bx (
b0 '
b0 &
0%
b0 $
b0 #
x"
bx !
$end
#2000
0,
04
0<
0D
0L
0+
#4000
07
bx0 )
00
#5000
0-
05
0=
0E
0M
#6000
03
#7000
0;
0C
0K
#8000
0?
bx00 )
08
#9000
0G
0O
0"
0@
0H
b0 )
0P
#10000
01
bx00 !
bx00 (
09
#13000
bx000 !
bx000 (
0A
#14000
0I
b0 !
b0 (
0Q
#100000
1.
16
1>
1F
1N
12
b1 R
1%
b11111 $
b11111 '
b10 #
b10 &
#102000
14
#104000
1?
b10 )
18
#105000
1-
1=
1E
1M
#107000
1;
#109000
1G
b110 )
1@
#110000
11
b10001 !
b10001 (
1Q
#111000
1C
#113000
1O
b1110 )
1H
#115000
1K
#117000
1"
b11110 )
1P
#118000
b1 !
b1 (
0Q
#200000
0.
02
1:
b10 R
0%
b11110 $
b11110 '
b100 #
b100 &
#202000
04
1<
#204000
0?
b11100 )
08
#205000
0-
15
0=
#206000
0;
#210000
01
b10 !
b10 (
19
#300000
1.
06
12
b11 R
1%
b11101 $
b11101 '
b110 #
b110 &
#305000
1-
#310000
b11 !
b11 (
11
#400000
0.
02
0:
1B
b100 R
0%
b11100 $
b11100 '
b1000 #
b1000 &
#402000
0<
1D
#404000
0G
b11000 )
0@
#405000
0-
05
1=
0E
#406000
0C
#410000
01
09
b100 !
b100 (
1A
#500000
1.
16
0>
12
b101 R
1%
b11011 $
b11011 '
b1010 #
b1010 &
#502000
14
#504000
1?
b11010 )
18
#505000
1-
0=
#510000
b101 !
b101 (
11
#600000
0.
02
1:
b110 R
0%
b11010 $
b11010 '
b1100 #
b1100 &
#602000
04
#604000
0?
b11000 )
08
#605000
0-
15
1=
#610000
01
b110 !
b110 (
19
#700000
1.
06
12
b111 R
1%
b11001 $
b11001 '
b1110 #
b1110 &
#705000
1-
#710000
b111 !
b111 (
11
#800000
0.
02
0:
0B
1J
b1000 R
0%
b11000 $
b11000 '
b10000 #
b10000 &
#802000
0D
1L
#804000
0O
b10000 )
0H
#805000
0-
05
0=
1E
0M
#806000
0K
#810000
01
09
0A
b1000 !
b1000 (
1I
#900000
1.
16
1>
0F
12
b1001 R
1%
b10111 $
b10111 '
b10010 #
b10010 &
#902000
14
#904000
1?
b10010 )
18
#905000
1-
1=
0E
#907000
1;
#909000
1G
b10110 )
1@
#910000
b1001 !
b1001 (
11
#1000000
0.
02
1:
b1010 R
0%
b10110 $
b10110 '
b10100 #
b10100 &
#1002000
04
1<
#1004000
0?
b10100 )
08
#1005000
0-
15
0=
#1006000
0;
#1010000
01
b1010 !
b1010 (
19
#1100000
1.
06
12
b1011 R
1%
b10101 $
b10101 '
b10110 #
b10110 &
#1105000
1-
#1110000
b1011 !
b1011 (
11
#1200000
0.
02
0:
1B
b1100 R
0%
b10100 $
b10100 '
b11000 #
b11000 &
#1202000
0<
#1204000
0G
b10000 )
0@
#1205000
0-
05
1=
1E
#1210000
01
09
b1100 !
b1100 (
1A
#1300000
1.
16
0>
12
b1101 R
1%
b10011 $
b10011 '
b11010 #
b11010 &
#1302000
14
#1304000
1?
b10010 )
18
#1305000
1-
0=
#1310000
b1101 !
b1101 (
11
#1400000
0.
02
1:
b1110 R
0%
b10010 $
b10010 '
b11100 #
b11100 &
#1402000
04
#1404000
0?
b10000 )
08
#1405000
0-
15
1=
#1410000
01
b1110 !
b1110 (
19
#1500000
1.
06
12
b1111 R
1%
b10001 $
b10001 '
b11110 #
b11110 &
#1505000
1-
#1510000
b1111 !
b1111 (
11
#1600000
0.
02
0:
0B
0J
b10000 R
0%
b10000 $
b10000 '
b0 #
b0 &
#1602000
0L
#1604000
0"
b0 )
0P
#1605000
0-
05
0=
0E
1M
#1610000
01
09
0A
0I
b10000 !
b10000 (
1Q
#1700000
1.
16
1>
1F
0N
12
b10001 R
1%
b1111 $
b1111 '
b10 #
b10 &
#1702000
14
#1704000
1?
b10 )
18
#1705000
1-
1=
1E
0M
#1707000
1;
#1709000
1G
b110 )
1@
#1710000
11
b1 !
b1 (
0Q
#1711000
1C
#1713000
1O
b1110 )
1H
#1718000
b10001 !
b10001 (
1Q
#1800000
0.
02
1:
b10010 R
0%
b1110 $
b1110 '
b100 #
b100 &
#1802000
04
1<
#1804000
0?
b1100 )
08
#1805000
0-
15
0=
#1806000
0;
#1810000
01
b10010 !
b10010 (
19
#1900000
1.
06
12
b10011 R
1%
b1101 $
b1101 '
b110 #
b110 &
#1905000
1-
#1910000
b10011 !
b10011 (
11
#2000000
0.
02
0:
1B
b10100 R
0%
b1100 $
b1100 '
b1000 #
b1000 &
#2002000
0<
1D
#2004000
0G
b1000 )
0@
#2005000
0-
05
1=
0E
#2006000
0C
#2010000
01
09
b10100 !
b10100 (
1A
#2100000
1.
16
0>
12
b10101 R
1%
b1011 $
b1011 '
b1010 #
b1010 &
#2102000
14
#2104000
1?
b1010 )
18
#2105000
1-
0=
#2110000
b10101 !
b10101 (
11
#2200000
0.
02
1:
b10110 R
0%
b1010 $
b1010 '
b1100 #
b1100 &
#2202000
04
#2204000
0?
b1000 )
08
#2205000
0-
15
1=
#2210000
01
b10110 !
b10110 (
19
#2300000
1.
06
12
b10111 R
1%
b1001 $
b1001 '
b1110 #
b1110 &
#2305000
1-
#2310000
b10111 !
b10111 (
11
#2400000
0.
02
0:
0B
1J
b11000 R
0%
b1000 $
b1000 '
b10000 #
b10000 &
#2402000
0D
#2404000
0O
b0 )
0H
#2405000
0-
05
0=
1E
1M
#2410000
01
09
0A
b11000 !
b11000 (
1I
#2500000
1.
16
1>
0F
12
b11001 R
1%
b111 $
b111 '
b10010 #
b10010 &
#2502000
14
#2504000
1?
b10 )
18
#2505000
1-
1=
0E
#2507000
1;
#2509000
1G
b110 )
1@
#2510000
b11001 !
b11001 (
11
#2600000
0.
02
1:
b11010 R
0%
b110 $
b110 '
b10100 #
b10100 &
#2602000
04
1<
#2604000
0?
b100 )
08
#2605000
0-
15
0=
#2606000
0;
#2610000
01
b11010 !
b11010 (
19
#2700000
1.
06
12
b11011 R
1%
b101 $
b101 '
b10110 #
b10110 &
#2705000
1-
#2710000
b11011 !
b11011 (
11
#2800000
0.
02
0:
1B
b11100 R
0%
b100 $
b100 '
b11000 #
b11000 &
#2802000
0<
#2804000
0G
b0 )
0@
#2805000
0-
05
1=
1E
#2810000
01
09
b11100 !
b11100 (
1A
#2900000
1.
16
0>
12
b11101 R
1%
b11 $
b11 '
b11010 #
b11010 &
#2902000
14
#2904000
1?
b10 )
18
#2905000
1-
0=
#2910000
b11101 !
b11101 (
11
#3000000
0.
02
1:
b11110 R
0%
b10 $
b10 '
b11100 #
b11100 &
#3002000
04
#3004000
0?
b0 )
08
#3005000
0-
15
1=
#3010000
01
b11110 !
b11110 (
19
#3100000
1.
06
12
b11111 R
1%
b1 $
b1 '
b11110 #
b11110 &
#3105000
1-
#3110000
b11111 !
b11111 (
11
#3200000
0.
02
0:
0B
0J
b100000 R
0%
b0 $
b0 '
b0 #
b0 &
