Aula 14/adder/adders.v
`timescale 1ns/1ps
// Somadores para usar no exercício.
// NÃO envie este arquivo para o juiz, ele já tem estes módulos.
module ha (
    input a,
    input b,
    output s,
    output co
);
    assign #5 s = a ^ b;
    assign #2 co = a & b;
endmodule

module fa (
    input a,
    input b,
    input ci,
    output s,
    output co
);
    wire axorb, and1, and2;
    assign #5 axorb = a ^ b;
    assign #5 s = axorb ^ ci;
    assign #2 and1 = axorb & ci;
    assign #2 and2 = a & b;
    assign #2 co = and1 | and2;
endmodule

Aula 14/adder/adders_tb.v
`timescale 1ns/1ps
// Testbench para os somadores (meio e completo)
// 1. Entenda o circuito gerado (no arquivo adders.v fornecido)
// 2. Execute este TB com:
//    iverilog -o adders_tb.o adders.v adders_tb.v
//    vvp adders_tb.o
// 3. Abra o arquivo gerado adders_tb.vcd com o GTKWave.
// 4. Estude atentamente a forma de onda. Observe o que acontece entre dois casos de teste e discuta com seu grupo.


module adders_tb;

    reg a,b,ci;
    wire ha_s, ha_co, fa_s, fa_co;

    ha dut_ha(a,b,ha_s,ha_co);
    fa dut_fa(a,b,ci,fa_s,fa_co);

    initial begin
        $dumpfile ("adders_tb.vcd");
        $dumpvars(0, adders_tb);   

        #20 a=1'b0; b=1'b0; ci=1'b0; 
        #20 a=1'b0; b=1'b0; ci=1'b1; 
        #20 a=1'b0; b=1'b1; ci=1'b0; 
        #20 a=1'b0; b=1'b1; ci=1'b1; 
        #20 a=1'b1; b=1'b0; ci=1'b0; 
        #20 a=1'b1; b=1'b0; ci=1'b1; 
        #20 a=1'b1; b=1'b1; ci=1'b0; 
        #20 a=1'b1; b=1'b1; ci=1'b1; 
        #20;
        $finish;
    end
    
endmodule

Aula 14/adder/adders_tb.vcd
$date
	Fri Oct  6 23:07:26 2023
$end
$version
	Icarus Verilog
$end
$timescale
	1ps
$end
$scope module adders_tb $end
$var wire 1 ! ha_s $end
$var wire 1 " ha_co $end
$var wire 1 # fa_s $end
$var wire 1 $ fa_co $end
$var reg 1 % a $end
$var reg 1 & b $end
$var reg 1 ' ci $end
$scope module dut_fa $end
$var wire 1 % a $end
$var wire 1 ( and1 $end
$var wire 1 ) and2 $end
$var wire 1 * axorb $end
$var wire 1 & b $end
$var wire 1 ' ci $end
$var wire 1 $ co $end
$var wire 1 # s $end
$upscope $end
$scope module dut_ha $end
$var wire 1 % a $end
$var wire 1 & b $end
$var wire 1 " co $end
$var wire 1 ! s $end
$upscope $end
$upscope $end
$enddefinitions $end
#0
$dumpvars
x*
x)
x(
x'
x&
x%
x$
x#
x"
x!
$end
#20000
0'
0&
0%
#22000
0(
0)
0"
#24000
0$
#25000
0*
0!
#30000
0#
#40000
1'
#45000
1#
#60000
0'
1&
#65000
0#
1*
1!
#70000
1#
#80000
1'
#82000
1(
#84000
1$
#85000
0#
#100000
0'
0&
1%
#102000
0(
#104000
0$
#105000
1#
#120000
1'
#122000
1(
#124000
1$
#125000
0#
#140000
0'
1&
#142000
0(
1)
1"
#145000
1#
0*
0!
#150000
0#
#160000
1'
#165000
1#
