Aula 14/adder/adders.v
`timescale 1ns/1ps
// Somadores para usar no exercício.
// NÃO envie este arquivo para o juiz, ele já tem estes módulos.
module ha (
    input a,
    input b,
    output s,
    output co
);
    assign #5 s = a ^ b;
    assign #2 co = a & b;
endmodule

module fa (
    input a,
    input b,
    input ci,
    output s,
    output co
);
    wire axorb, and1, and2;
    assign #5 axorb = a ^ b;
    assign #5 s = axorb ^ ci;
    assign #2 and1 = axorb & ci;
    assign #2 and2 = a & b;
    assign #2 co = and1 | and2;
endmodule

Aula 14/adder/adder_cl.v
module adder_cl 
    #(parameter N=4)
     (input [N-1:0] a,
      input [N-1:0] b,
      input ci,
      output [N-1:0] s,
      output co);
    // Escreva sua solução a partir daqui
    wire [N:0] carry;
    wire [N-1:0] gen;
    wire [N-1:0] prop;
    assign carry[0] = 0;
    genvar i;
    generate
      for (i = 0; i < N; i = i + 1) begin
        // Instantiate a single-bit full adder for each bit position, ignoring Cout
        fa fa_inst (
          .a(a[i]),
          .b(b[i]),
          .ci(carry[i]), 
          .s(s[i]),
          .co()
        );
      end
      for (i = 0; i < N; i = i + 1) begin
        // Propagate and Generate
        assign prop[i] = a[i] | b[i];
        assign gen[i] = a[i] & b[i];
      end
      for (i = 0; i < N; i = i + 1) begin
        // Recursive carries
        assign carry[i+1] = gen[i] | (prop[i] & carry[i]);
      end
      assign co = carry[N];
    endgenerate

endmodule

Aula 14/adder/adder_cl_tb.v
`timescale 1ns/1ps

module adder_cl_tb;

    parameter N = 4;
    reg [N-1:0] a;
    reg [N-1:0] b;
    reg ci;
    wire [N-1:0] s;
    wire co;

    adder_cl #(N) dut_cla(
        .a(a),
        .b(b),
        .ci(ci),
        .s(s),
        .co(co)
    );

  initial begin
    $dumpfile ("adder_cl_tb.vcd");
    $dumpvars(0, adder_cl_tb);
    // Initialize inputs
    a = 4'b0000;
    b = 4'b0000;
    ci = 0;
    //integer i;

    // Apply inputs and observe outputs
    $display("s must start at 0000 and increment by 1 after each line");
    $display("Time a b ci | s co");
    $display("--------------------");
    for (integer i = 0; i < 16; i = i + 1) begin
      #20; // Wait for one clock cycle
      $display("%t %b %b  %b | %b  %b", $time, a, b, ci, s, co);
      // Increment inputs for the next iteration
      a = a + 2;
      b = b - 1;
      ci = ~ci;
    end

    $finish; // End simulation
  end
    
endmodule

Aula 14/adder/adder_cl_tb.vcd
$date
	Fri Oct  6 23:05:09 2023
$end
$version
	Icarus Verilog
$end
$timescale
	1ps
$end
$scope module adder_cl_tb $end
$var wire 5 ! s [4:0] $end
$var wire 1 " co $end
$var reg 5 # a [4:0] $end
$var reg 5 $ b [4:0] $end
$var reg 1 % ci $end
$scope module dut_cla $end
$var wire 5 & a [4:0] $end
$var wire 5 ' b [4:0] $end
$var wire 1 % ci $end
$var wire 5 ( s [4:0] $end
$var wire 5 ) prop [4:0] $end
$var wire 5 * gen [4:0] $end
$var wire 1 " co $end
$var wire 6 + carry [5:0] $end
$scope begin genblk1[0] $end
$scope module fa_inst $end
$var wire 1 , a $end
$var wire 1 - and1 $end
$var wire 1 . and2 $end
$var wire 1 / axorb $end
$var wire 1 0 b $end
$var wire 1 1 ci $end
$var wire 1 2 co $end
$var wire 1 3 s $end
$upscope $end
$upscope $end
$scope begin genblk1[1] $end
$scope module fa_inst $end
$var wire 1 4 a $end
$var wire 1 5 and1 $end
$var wire 1 6 and2 $end
$var wire 1 7 axorb $end
$var wire 1 8 b $end
$var wire 1 9 ci $end
$var wire 1 : co $end
$var wire 1 ; s $end
$upscope $end
$upscope $end
$scope begin genblk1[2] $end
$scope module fa_inst $end
$var wire 1 < a $end
$var wire 1 = and1 $end
$var wire 1 > and2 $end
$var wire 1 ? axorb $end
$var wire 1 @ b $end
$var wire 1 A ci $end
$var wire 1 B co $end
$var wire 1 C s $end
$upscope $end
$upscope $end
$scope begin genblk1[3] $end
$scope module fa_inst $end
$var wire 1 D a $end
$var wire 1 E and1 $end
$var wire 1 F and2 $end
$var wire 1 G axorb $end
$var wire 1 H b $end
$var wire 1 I ci $end
$var wire 1 J co $end
$var wire 1 K s $end
$upscope $end
$upscope $end
$scope begin genblk1[4] $end
$scope module fa_inst $end
$var wire 1 L a $end
$var wire 1 M and1 $end
$var wire 1 N and2 $end
$var wire 1 O axorb $end
$var wire 1 P b $end
$var wire 1 Q ci $end
$var wire 1 R co $end
$var wire 1 S s $end
$upscope $end
$upscope $end
$scope begin genblk2[0] $end
$upscope $end
$scope begin genblk2[1] $end
$upscope $end
$scope begin genblk2[2] $end
$upscope $end
$scope begin genblk2[3] $end
$upscope $end
$scope begin genblk2[4] $end
$upscope $end
$scope begin genblk3[0] $end
$upscope $end
$scope begin genblk3[1] $end
$upscope $end
$scope begin genblk3[2] $end
$upscope $end
$scope begin genblk3[3] $end
$upscope $end
$scope begin genblk3[4] $end
$upscope $end
$upscope $end
$scope begin $ivl_for_loop0 $end
$var integer 32 T i [31:0] $end
$upscope $end
$upscope $end
$enddefinitions $end
#0
$dumpvars
b0 T
xS
xR
0Q
0P
xO
xN
xM
0L
xK
xJ
0I
0H
xG
xF
xE
0D
xC
xB
0A
0@
x?
x>
x=
0<
x;
x:
09
08
x7
x6
x5
04
x3
x2
01
00
x/
x.
x-
0,
b0 +
b0 *
b0 )
bx (
b0 '
b0 &
0%
b0 $
b0 #
0"
bx !
$end
#2000
0=
0E
0M
05
0.
06
0>
0F
0N
0-
#4000
0:
0B
0J
0R
02
#5000
0/
07
0?
0G
0O
#10000
03
0;
0C
0K
b0 !
b0 (
0S
#100000
1"
1Q
1I
1A
b111100 +
b11111 )
b10 *
10
18
1@
1H
1P
14
b1 T
1%
b11111 $
b11111 '
b10 #
b10 &
#102000
16
#104000
1:
#105000
1S
1K
b11100 !
b11100 (
1C
1/
1?
1G
1O
#107000
1=
1E
1M
#109000
1B
1J
1R
#110000
13
0C
0K
b1 !
b1 (
0S
#200000
0A
b111000 +
b11110 )
b100 *
00
04
1<
b10 T
0%
b11110 $
b11110 '
b100 #
b100 &
#202000
0=
06
1>
#204000
0:
#205000
b101 !
b101 (
1C
0/
17
0?
#210000
03
1;
b10 !
b10 (
0C
#300000
b11111 )
10
08
14
b11 T
1%
b11101 $
b11101 '
b110 #
b110 &
#305000
1/
#310000
b11 !
b11 (
13
#400000
0I
b110000 +
b11100 )
b1000 *
00
04
0<
1D
b100 T
0%
b11100 $
b11100 '
b1000 #
b1000 &
#402000
0E
0>
1F
#404000
0B
#405000
b1011 !
b1011 (
1K
0/
07
1?
0G
#410000
03
0;
1C
b100 !
b100 (
0K
#500000
1A
b110100 +
b11011 )
b1010 *
10
18
0@
14
b101 T
1%
b11011 $
b11011 '
b1010 #
b1010 &
#502000
1=
16
#504000
1B
1:
#505000
b0 !
b0 (
0C
1/
0?
#507000
0=
#509000
0B
#510000
13
b101 !
b101 (
1C
#600000
0I
0A
b110000 +
b1000 *
b11110 )
00
04
1<
b110 T
0%
b11010 $
b11010 '
b1100 #
b1100 &
#602000
06
#604000
0:
#605000
b1 !
b1 (
0C
0/
17
1?
#610000
03
1;
b110 !
b110 (
1C
#700000
b11111 )
10
08
14
b111 T
1%
b11001 $
b11001 '
b1110 #
b1110 &
#705000
1/
#710000
b111 !
b111 (
13
#800000
0Q
b100000 +
b11000 )
b10000 *
00
04
0<
0D
1L
b1000 T
0%
b11000 $
b11000 '
b10000 #
b10000 &
#802000
0M
0F
1N
#804000
0J
#805000
b10111 !
b10111 (
1S
0/
07
0?
1G
0O
#810000
03
0;
0C
1K
b1000 !
b1000 (
0S
#900000
1I
1A
b101100 +
b10111 )
b10010 *
10
18
1@
0H
14
b1001 T
1%
b10111 $
b10111 '
b10010 #
b10010 &
#902000
1E
16
#904000
1J
1:
#905000
0K
b100 !
b100 (
1C
1/
1?
0G
#907000
1=
0E
#909000
1B
0J
#910000
13
0C
b1001 !
b1001 (
1K
#1000000
0A
b101000 +
b10110 )
b10100 *
00
04
1<
b1010 T
0%
b10110 $
b10110 '
b10100 #
b10100 &
#1002000
0=
06
1>
#1004000
0:
#1005000
b1101 !
b1101 (
1C
0/
17
0?
#1010000
03
1;
b1010 !
b1010 (
0C
#1100000
b10111 )
10
08
14
b1011 T
1%
b10101 $
b10101 '
b10110 #
b10110 &
#1105000
1/
#1110000
b1011 !
b1011 (
13
#1200000
0Q
0I
b100000 +
b10000 *
b11100 )
00
04
0<
1D
b1100 T
0%
b10100 $
b10100 '
b11000 #
b11000 &
#1202000
0>
#1204000
0B
#1205000
b11 !
b11 (
0K
0/
07
1?
1G
#1210000
03
0;
1C
b1100 !
b1100 (
1K
#1300000
1A
b100100 +
b11011 )
b10010 *
10
18
0@
14
b1101 T
1%
b10011 $
b10011 '
b11010 #
b11010 &
#1302000
1=
16
#1304000
1B
1:
#1305000
b1000 !
b1000 (
0C
1/
0?
#1307000
0=
#1309000
0B
#1310000
13
b1101 !
b1101 (
1C
#1400000
0Q
0I
0A
b100000 +
b10000 *
b11110 )
00
04
1<
b1110 T
0%
b10010 $
b10010 '
b11100 #
b11100 &
#1402000
06
#1404000
0:
#1405000
b1001 !
b1001 (
0C
0/
17
1?
#1410000
03
1;
b1110 !
b1110 (
1C
#1500000
b11111 )
10
08
14
b1111 T
1%
b10001 $
b10001 '
b11110 #
b11110 &
#1505000
1/
#1510000
b1111 !
b1111 (
13
#1600000
0"
b0 +
b10000 )
b0 *
00
04
0<
0D
0L
b10000 T
0%
b10000 $
b10000 '
b0 #
b0 &
#1602000
0N
#1604000
0R
#1605000
0/
07
0?
0G
1O
#1610000
03
0;
0C
0K
b10000 !
b10000 (
1S
#1700000
1Q
1I
1A
b11100 +
b1111 )
b10 *
10
18
1@
1H
0P
14
b10001 T
1%
b1111 $
b1111 '
b10 #
b10 &
#1702000
1M
16
#1704000
1R
1:
#1705000
0S
1K
b1100 !
b1100 (
1C
1/
1?
1G
0O
#1707000
1=
1E
0M
#1709000
1B
1J
0R
#1710000
13
0C
0K
b10001 !
b10001 (
1S
#1800000
0A
b11000 +
b1110 )
b100 *
00
04
1<
b10010 T
0%
b1110 $
b1110 '
b100 #
b100 &
#1802000
0=
06
1>
#1804000
0:
#1805000
b10101 !
b10101 (
1C
0/
17
0?
#1810000
03
1;
b10010 !
b10010 (
0C
#1900000
b1111 )
10
08
14
b10011 T
1%
b1101 $
b1101 '
b110 #
b110 &
#1905000
1/
#1910000
b10011 !
b10011 (
13
#2000000
0I
b10000 +
b1100 )
b1000 *
00
04
0<
1D
b10100 T
0%
b1100 $
b1100 '
b1000 #
b1000 &
#2002000
0E
0>
1F
#2004000
0B
#2005000
b11011 !
b11011 (
1K
0/
07
1?
0G
#2010000
03
0;
1C
b10100 !
b10100 (
0K
#2100000
1A
b10100 +
b1011 )
b1010 *
10
18
0@
14
b10101 T
1%
b1011 $
b1011 '
b1010 #
b1010 &
#2102000
1=
16
#2104000
1B
1:
#2105000
b10000 !
b10000 (
0C
1/
0?
#2107000
0=
#2109000
0B
#2110000
13
b10101 !
b10101 (
1C
#2200000
0I
0A
b10000 +
b1000 *
b1110 )
00
04
1<
b10110 T
0%
b1010 $
b1010 '
b1100 #
b1100 &
#2202000
06
#2204000
0:
#2205000
b10001 !
b10001 (
0C
0/
17
1?
#2210000
03
1;
b10110 !
b10110 (
1C
#2300000
b1111 )
10
08
14
b10111 T
1%
b1001 $
b1001 '
b1110 #
b1110 &
#2305000
1/
#2310000
b10111 !
b10111 (
13
#2400000
0"
0Q
b0 +
b0 *
b11000 )
00
04
0<
0D
1L
b11000 T
0%
b1000 $
b1000 '
b10000 #
b10000 &
#2402000
0F
#2404000
0J
#2405000
b111 !
b111 (
0S
0/
07
0?
1G
1O
#2410000
03
0;
0C
1K
b11000 !
b11000 (
1S
#2500000
1I
1A
b1100 +
b10111 )
b10 *
10
18
1@
0H
14
b11001 T
1%
b111 $
b111 '
b10010 #
b10010 &
#2502000
1E
16
#2504000
1J
1:
#2505000
0K
b10100 !
b10100 (
1C
1/
1?
0G
#2507000
1=
0E
#2509000
1B
0J
#2510000
13
0C
b11001 !
b11001 (
1K
#2600000
0A
b1000 +
b10110 )
b100 *
00
04
1<
b11010 T
0%
b110 $
b110 '
b10100 #
b10100 &
#2602000
0=
06
1>
#2604000
0:
#2605000
b11101 !
b11101 (
1C
0/
17
0?
#2610000
03
1;
b11010 !
b11010 (
0C
#2700000
b10111 )
10
08
14
b11011 T
1%
b101 $
b101 '
b10110 #
b10110 &
#2705000
1/
#2710000
b11011 !
b11011 (
13
#2800000
0"
0Q
0I
b0 +
b0 *
b11100 )
00
04
0<
1D
b11100 T
0%
b100 $
b100 '
b11000 #
b11000 &
#2802000
0>
#2804000
0B
#2805000
b10011 !
b10011 (
0K
0/
07
1?
1G
#2810000
03
0;
1C
b11100 !
b11100 (
1K
#2900000
1A
b100 +
b11011 )
b10 *
10
18
0@
14
b11101 T
1%
b11 $
b11 '
b11010 #
b11010 &
#2902000
1=
16
#2904000
1B
1:
#2905000
b11000 !
b11000 (
0C
1/
0?
#2907000
0=
#2909000
0B
#2910000
13
b11101 !
b11101 (
1C
#3000000
0"
0Q
0I
0A
b0 +
b0 *
b11110 )
00
04
1<
b11110 T
0%
b10 $
b10 '
b11100 #
b11100 &
#3002000
06
#3004000
0:
#3005000
b11001 !
b11001 (
0C
0/
17
1?
#3010000
03
1;
b11110 !
b11110 (
1C
#3100000
b11111 )
10
08
14
b11111 T
1%
b1 $
b1 '
b11110 #
b11110 &
#3105000
1/
#3110000
b11111 !
b11111 (
13
#3200000
b0 )
00
04
0<
0D
0L
b100000 T
0%
b0 $
b0 '
b0 #
b0 &
